pipeclip/Alignment.py
pipeclip/CLIP.py
pipeclip/Enrich.py
pipeclip/Utils.py
pipeclip/ZTNB_tryCatch.R
pipeclip/__init__.py
pipeclip/barcode_removal.py
pipeclip/main.py
pipeclip/mutation.py
pipeclip/runR1.sh
pipeclip-2.0.10.dist-info/entry_points.txt
pipeclip-2.0.10.dist-info/LICENSE
pipeclip-2.0.10.dist-info/WHEEL
pipeclip-2.0.10.dist-info/METADATA
pipeclip-2.0.10.dist-info/RECORD
