Metadata-Version: 2.1
Name: pipeclip
Version: 2.0.10
Summary: PIPELINE FOR CLIP SEQ DATA
Home-page: https://github.com/y9c/PIPE-CLIP
Keywords: bioinformatics,CLIP,PAR-CLIP,iCLIP,RNA-protein interaction,mutation,truncation
Author: Chang Ye
Author-email: yech1990@gmail.com
Requires-Python: >=3.6,<4.0
Classifier: Programming Language :: Python :: 3
Classifier: Programming Language :: Python :: 3.6
Classifier: Programming Language :: Python :: 3.7
Classifier: Programming Language :: Python :: 3.8
Classifier: Programming Language :: Python :: 3.9
Requires-Dist: click (>=8.1.2,<9.0.0)
Requires-Dist: colorama (>=0.4.4,<0.5.0)
Requires-Dist: pybedtools (>=0.9.0,<0.10.0)
Requires-Dist: pysam (>=0.19.0,<0.20.0)
Requires-Dist: rpy2 (>=3.5.1,<4.0.0)
Project-URL: Repository, https://github.com/y9c/PIPE-CLIP
